netstorage
