Metadata-Version: 1.0
Name: netstorage
Version: 0.0.9
Summary: A python wrapper for Akamais Nestorage API
Home-page: UNKNOWN
Author: Matt Chung
Author-email: mchung@whalerockindustries.com
License: UNKNOWN
Platform: UNKNOWN
